gfxlcd/__init__.py
gfxlcd/abstract/__init__.py
gfxlcd/abstract/chip.py
gfxlcd/abstract/driver.py
gfxlcd/abstract/font.py
gfxlcd/abstract/touch.py
gfxlcd/demos/ili9325.py
gfxlcd/demos/ili9325_2.py
gfxlcd/demos/ili9325_hd44780.py
gfxlcd/demos/ili9325_image.py
gfxlcd/demos/ili9325_text.py
gfxlcd/demos/ili9486.py
gfxlcd/demos/ili9486_image.py
gfxlcd/demos/nju.py
gfxlcd/demos/nju_2.py
gfxlcd/demos/nju_3.py
gfxlcd/demos/nju_hd44780.py
gfxlcd/demos/nju_image.py
gfxlcd/demos/nju_image_1.py
gfxlcd/demos/nju_text.py
gfxlcd/demos/sh1106.py
gfxlcd/demos/sh1106_1.py
gfxlcd/demos/sh1106_2.py
gfxlcd/demos/sh1106_3.py
gfxlcd/demos/sh1106_hd44780.py
gfxlcd/demos/sh1106_image.py
gfxlcd/demos/ssd.py
gfxlcd/demos/ssd_2.py
gfxlcd/demos/ssd_3.py
gfxlcd/demos/ssd_hd44780.py
gfxlcd/demos/ssd_image.py
gfxlcd/demos/ssd_image_1.py
gfxlcd/demos/ssd_text.py
gfxlcd/demos/touch_240x320.py
gfxlcd/demos/touch_480x320.py
gfxlcd/demos/touch_loop.py
gfxlcd/drawing/__init__.py
gfxlcd/drawing/area.py
gfxlcd/drawing/page.py
gfxlcd/drawing/pixel.py
gfxlcd/driver/__init__.py
gfxlcd/driver/hd44780.py
gfxlcd/driver/ad7843/__init__.py
gfxlcd/driver/ad7843/ad7843.py
gfxlcd/driver/ili9325/__init__.py
gfxlcd/driver/ili9325/gpio.py
gfxlcd/driver/ili9325/ili9325.py
gfxlcd/driver/ili9486/__init__.py
gfxlcd/driver/ili9486/ili9486.py
gfxlcd/driver/ili9486/spi.py
gfxlcd/driver/nju6450/__init__.py
gfxlcd/driver/nju6450/gpio.py
gfxlcd/driver/nju6450/nju6450.py
gfxlcd/driver/null/__init__.py
gfxlcd/driver/null/area_driver.py
gfxlcd/driver/null/null_area.py
gfxlcd/driver/null/null_page.py
gfxlcd/driver/sh1106/__init__.py
gfxlcd/driver/sh1106/sh1106.py
gfxlcd/driver/sh1106/spi.py
gfxlcd/driver/ssd1306/__init__.py
gfxlcd/driver/ssd1306/spi.py
gfxlcd/driver/ssd1306/ssd1306.py
gfxlcd/driver/xpt2046/__init__.py
gfxlcd/driver/xpt2046/xpt2046.py
gfxlcd/font/__init__.py
gfxlcd/font/font8x8.py
gfxlcd/font/scalable_font.py
gfxlcd/tests/test_area_drawing.py
gfxlcd/tests/test_chip.py
gfxlcd/tests/test_hd44780.py
GfxLCD-0.8.5.dist-info/LICENSE
GfxLCD-0.8.5.dist-info/METADATA
GfxLCD-0.8.5.dist-info/WHEEL
GfxLCD-0.8.5.dist-info/top_level.txt
GfxLCD-0.8.5.dist-info/RECORD
