Metadata-Version: 2.1
Name: GfxLCD
Version: 0.8.5
Summary: gfxlcd is a lib for graphical lcds: ILI9328, SSD1306, SH1106, NJU6450, touch panel: AD7843 @ Raspberry Pi.
Author-email: Bartosz Kościów <kosci1@gmail.com>
License: Copyright (c) 2017 Bartosz Kościów <kosci1@gmail.com>
Project-URL: Homepage, https://github.com/bkosciow/gfxlcd
Keywords: gfxlcd,raspberry pi,ili9328,ssd1306,nju6450,lcd,graphical lcd,touch panel,ad7843,ili9486,xpt2046,ad7846,sh1106
Classifier: Development Status :: 4 - Beta
Classifier: Environment :: Console
Classifier: Intended Audience :: Developers
Classifier: Natural Language :: English
Classifier: License :: OSI Approved :: MIT License
Classifier: Operating System :: OS Independent
Classifier: Programming Language :: Python
Classifier: Programming Language :: Python :: 3
Classifier: Topic :: Software Development :: Libraries :: Python Modules
Classifier: Topic :: Home Automation
License-File: LICENSE
